{"cameraMode":{"drawMode":0,"name":"Shaded","section":"Shading Mode"},"sceneLighting":true,"audioPlay":false,"sceneViewState":{"m_AlwaysRefresh":false,"showFog":true,"showSkybox":true,"showFlares":true,"showImageEffects":true,"showParticleSystems":true,"showVisualEffectGraphs":true,"m_FxEnabled":true},"in2DMode":false,"pivot":{"x":-0.7302613258361816,"y":0.9539999961853027,"z":4.336740016937256},"rotation":{"x":0.05376077815890312,"y":0.24605605006217957,"z":-0.013670643791556359,"w":0.9676703810691834},"size":0.6547986268997192,"orthographic":false}